cpr_generator/__init__.py
cpr_generator/cpr_number.py
cpr_generator/cpr_verifier.py
cpr_generator/generator.py
cpr_generator/server.py
cpr_generator-0.2.2.dist-info/LICENSE
cpr_generator-0.2.2.dist-info/METADATA
cpr_generator-0.2.2.dist-info/WHEEL
cpr_generator-0.2.2.dist-info/entry_points.txt
cpr_generator-0.2.2.dist-info/top_level.txt
cpr_generator-0.2.2.dist-info/RECORD
