Metadata-Version: 2.1
Name: cpr-generator
Version: 0.2.2
Summary: An unofficial tool for generating and verifying Danish CPR-numbers.
Author-email: HackTheOxidation <tomas.hagenau@protonmail.ch>
License: Copyright (c) 2023 HackTheOxidation
Project-URL: Homepage, https://codeberg.org/HackTheOxidation/cpr-generator
Project-URL: Bug Tracker, https://codeberg.org/HackTheOxidation/cpr-generator/issues
Classifier: Programming Language :: Python :: 3
Classifier: License :: OSI Approved :: MIT License
Classifier: Operating System :: OS Independent
Requires-Python: >=3.10
License-File: LICENSE
Requires-Dist: flask
Requires-Dist: markupsafe
